Battlefield-1.0.3.dist-info/DESCRIPTION.rst
Battlefield-1.0.3.dist-info/LICENSE.txt
Battlefield-1.0.3.dist-info/METADATA
Battlefield-1.0.3.dist-info/RECORD
Battlefield-1.0.3.dist-info/WHEEL
Battlefield-1.0.3.dist-info/metadata.json
Battlefield-1.0.3.dist-info/top_level.txt
battlefield/__init__.py
battlefield/engine/__init__.py
battlefield/engine/base.py
battlefield/engine/config.py
battlefield/engine/robot.py
battlefield/engine/turn.py
battlefield/robot/__init__.py
battlefield/robot/robot.py
