Metadata-Version: 2.0
Name: Battlefield
Version: 1.0.3
Summary: Utilities to create games and robots for Battlefield
Home-page: https://github.com/tehpug/Battlefield
Author: Mehdy Khoshnoody
Author-email: mehdy.khoshnoody@gmail.com
License: GPLv3
Keywords: robot game battlefield
Platform: UNKNOWN
Classifier: Development Status :: 3 - Alpha
Classifier: Intended Audience :: Developers
Classifier: Topic :: Software Development :: Libraries :: Python Modules
Classifier: License :: OSI Approved :: GNU General Public License v3 (GPLv3)
Classifier: Programming Language :: Python :: 3
Classifier: Programming Language :: Python :: 3.3
Classifier: Programming Language :: Python :: 3.4
Classifier: Programming Language :: Python :: 3.5
Requires-Dist: pika
